squeal/__init__.py
squeal/buffer.py
squeal/queue.py
squeal/utils.py
squeal/backend/__init__.py
squeal/backend/base.py
squeal/backend/local.py
squeal/backend/mysql.py
squeal-0.0.17.dist-info/LICENSE
squeal-0.0.17.dist-info/METADATA
squeal-0.0.17.dist-info/WHEEL
squeal-0.0.17.dist-info/top_level.txt
squeal-0.0.17.dist-info/RECORD
