Metadata-Version: 2.1
Name: squeal
Version: 0.0.17
Summary: Message queue backed by a database
Author-email: Alex Dodge <alexdodge@gmail.com>
License: MIT License
Project-URL: Library Homepage, https://github.com/adodge/squeal
Project-URL: Library Bug Tracker, https://github.com/adodge/squeal/issues
Keywords: message queue
Classifier: Development Status :: 2 - Pre-Alpha
Classifier: Programming Language :: Python :: 3
Classifier: License :: OSI Approved :: MIT License
Requires-Python: <4,>=3.8
License-File: LICENSE
